{
  "Registers": [
    {
      "Address": "0x90",
      "Name": "MAIN_CTRL_SHR1",
	  "Description": "NVM main control shadow register 1",
      "Size": "0x1",
      "Fields": [
        {
          "Bit": {
            "Name": "AUTO_TURN_ON",
            "Description": "0: PMIC does not start automatically on VIN rising\n1: PMIC starts automatically on VIN rising",
            "BitOffset": "0x0",
            "BitWidth": "0x1",
            "Access": "RW",
            "PossibleValues": {
              "0x0": "Yes",
              "0x1": "No"
            }
          }
        },
        {
          "Bit": {
            "Name": "WDG_EN",
            "Description": "NVM Watchdog default value",
            "BitOffset": "0x1",
            "BitWidth": "0x1",
            "Access": "RW",
            "PossibleValues": {
              "0x0": "Disable",
              "0x1": "Enable"
            }
          }
        },
		{
          "Bit": {
            "Name": "TMR_SET",
            "Description": "Watchdog timer duration default value",
            "BitOffset": "0x2",
            "BitWidth": "0x2",
            "Access": "RW",
			"PossibleValues": {
              "0x0": "10s",
              "0x1": "20s",
              "0x2": "50s",
              "0x3": "100s"
            }
          }
        },
		{
          "Bit": {
            "Name": "VINOK_RISE",
            "Description": "VINOK_RISE threshold voltage",
            "BitOffset": "0x4",
            "BitWidth": "0x2",
            "Access": "RW",
			"PossibleValues": {
              "0x0": "3.1V",
              "0x1": "3.3V",
              "0x2": "3.5V",
              "0x3": "4.0V"
            }
          }
        },
		{
          "Bit": {
            "Name": "VINOK_HYST",
            "Description": "VINOK_HYST threshold voltage",
            "BitOffset": "0x6",
            "BitWidth": "0x2",
            "Access": "RW",
			"PossibleValues": {
              "0x0": "200mV",
              "0x1": "300mV",
              "0x2": "400mV",
              "0x3": "500mV"
            }
          }
        }
      ]
    },
	
    {
      "Address": "0x91",
      "Name": "MAIN_CTRL_SHR2",
	  "Description": "NVM main control shadow register 2",
      "Size": "0x1",
      "Fields": [
        {
          "Bit": {
            "Name": "PKEY_LKP_TMR",
            "Description": "PONKEYn long key press timer duration default value",
            "BitOffset": "0x0",
            "BitWidth": "0x2",
            "Access": "RW",
            "PossibleValues": {
              "0x0": "2s",
              "0x1": "5s",
			  "0x2": "10s",
              "0x3": "15s"
            }
          }
        },
        {
          "Bit": {
            "Name": "PKEY_LKP_EN_FSLS",
            "Description": "PONKEYn Long Key Press Fail-Safe-Lock-Skip bit or EN deasserted Fail-Safe-Lock-Skip bit\n0: No effect\n1: A PONKEYn long key press or a EN deassertion",
            "BitOffset": "0x2",
            "BitWidth": "0x1",
            "Access": "RW",
            "PossibleValues": {
              "0x0": "No",
              "0x1": "Yes"
            }
          }
        },
		{
          "Bit": {
            "Name": "PKEY_LKP_OFF",
            "Description": "PONKEYn long key press turn-off condition default value",
            "BitOffset": "0x3",
            "BitWidth": "0x2",
            "Access": "RW",
			"PossibleValues": {
              "0x0": "No",
              "0x1": "Yes"
            }
          }
        },
		{
          "Bit": {
            "Name": "RST_DLY",
            "Description": "RST release delay after POWER_UP sequence",
            "BitOffset": "0x4",
            "BitWidth": "0x2",
            "Access": "RW",
			"PossibleValues": {
              "0x0": "0ms",
              "0x1": "1.5ms",
              "0x2": "3ms",
              "0x3": "6ms"
            }
          }
        },
		{
          "Bit": {
            "Name": "RANK_DLY",
            "Description": "power-up/power-down step (RANK) duration",
            "BitOffset": "0x6",
            "BitWidth": "0x2",
            "Access": "RW",
			"PossibleValues": {
              "0x0": "1.5ms",
              "0x1": "3ms",
              "0x2": "4.5ms",
              "0x3": "6ms"
            }
          }
        }
      ]
    },
	
	{
      "Address": "0x92",
      "Name": "RANK_SHR1",
	  "Description": "NVM rank shadow register 1",
      "Size": "0x1",
      "Fields": [
        {
          "Bit": {
            "Name": "BUCK1_RANK",
            "Description": "-",
            "BitOffset": "0x0",
            "BitWidth": "0x3",
            "Access": "RW",
            "PossibleValues": {
              "0x0": "rank0",
              "0x1": "rank1",
			  "0x2": "rank2",
              "0x3": "rank3",
			  "0x4": "rank4",
              "0x5": "rank5",
			  "0x6": "rank0",
              "0x7": "rank0"
            }
          }
        },
        {
          "Bit": {
            "Name": "BUCK2_RANK",
            "Description": "-",
            "BitOffset": "0x3",
            "BitWidth": "0x3",
            "Access": "RW",
            "PossibleValues": {
              "0x0": "rank0",
              "0x1": "rank1",
			  "0x2": "rank2",
              "0x3": "rank3",
			  "0x4": "rank4",
              "0x5": "rank5",
			  "0x6": "rank0",
              "0x7": "rank0"
            }
          }
        }
      ]
    },
	
	{
		"Address": "0x93",
		"Name": "Reserved",
		"Description": "-",
		"Size": "0x1",
		"Fields": [
			{
				"Bit": {
					"Name": "Reserved",
					"Description": "-",
					"BitOffset": "0x0",
					"BitWidth": "0x8",
					"Access": "R"
				}
			}
		]
    },
	
	{
      "Address": "0x94",
      "Name": "FREE_SHR1",
	  "Description": "FREE_SHR1",
      "Size": "0x1",
      "Fields": [
        {
          "Bit": {
            "Name": "FREE_SHR1",
            "Description": "-",
            "BitOffset": "0x0",
            "BitWidth": "0x8",
            "Access": "RW"
          }
        }
      ]
    },
	
	{
      "Address": "0x95",
      "Name": "FREE_SHR2",
	  "Description": "FREE_SHR2",
      "Size": "0x1",
      "Fields": [
        {
          "Bit": {
            "Name": "FREE_SHR2",
            "Description": "-",
            "BitOffset": "0x0",
            "BitWidth": "0x8",
            "Access": "RW"
          }
        }
      ]
    },
	
	{
      "Address": "0x96",
      "Name": "RANK_SHR5",
	  "Description": "NVM rank shadow register 5",
      "Size": "0x1",
      "Fields": [
        {
          "Bit": {
            "Name": "LDO2_RANK",
            "Description": "-",
            "BitOffset": "0x3",
            "BitWidth": "0x3",
            "Access": "RW",
            "PossibleValues": {
              "0x0": "rank0",
              "0x1": "rank1",
			  "0x2": "rank2",
              "0x3": "rank3",
			  "0x4": "rank4",
              "0x5": "rank5",
			  "0x6": "rank0",
              "0x7": "rank0"
            }
          }
        }
      ]
    },
	
	{
      "Address": "0x97",
      "Name": "RANK_SHR6",
	  "Description": "NVM rank shadow register 6",
      "Size": "0x1",
      "Fields": [
        {
          "Bit": {
            "Name": "LDO3_RANK",
            "Description": "-",
            "BitOffset": "0x0",
            "BitWidth": "0x3",
            "Access": "RW",
            "PossibleValues": {
              "0x0": "rank0",
              "0x1": "rank1",
			  "0x2": "rank2",
              "0x3": "rank3",
			  "0x4": "rank4",
              "0x5": "rank5",
			  "0x6": "rank0",
              "0x7": "rank0"
            }
          }
        },
        {
          "Bit": {
            "Name": "LDO4_RANK",
            "Description": "-",
            "BitOffset": "0x3",
            "BitWidth": "0x3",
            "Access": "RW",
            "PossibleValues": {
              "0x0": "rank0",
              "0x1": "rank1",
			  "0x2": "rank2",
              "0x3": "rank3",
			  "0x4": "rank4",
              "0x5": "rank5",
			  "0x6": "rank0",
              "0x7": "rank0"
            }
          }
        }
      ]
    },
	
	{
      "Address": "0x98",
      "Name": "RANK_SHR7",
	  "Description": "NVM rank shadow register 7",
      "Size": "0x1",
      "Fields": [
        {
          "Bit": {
            "Name": "LDO5_RANK",
            "Description": "-",
            "BitOffset": "0x0",
            "BitWidth": "0x3",
            "Access": "RW",
            "PossibleValues": {
              "0x0": "rank0",
              "0x1": "rank1",
			  "0x2": "rank2",
              "0x3": "rank3",
			  "0x4": "rank4",
              "0x5": "rank5",
			  "0x6": "rank0",
              "0x7": "rank0"
            }
          }
        }
      ]
    },
	
	{
		"Address": "0x99",
		"Name": "Reserved",
		"Description": "-",
		"Size": "0x1",
		"Fields": [
			{
				"Bit": {
					"Name": "Reserved",
					"Description": "-",
					"BitOffset": "0x0",
					"BitWidth": "0x8",
					"Access": "R"
				}
			}
		]
    },
	
	{
      "Address": "0x9A",
      "Name": "BUCK_MODE_SHR1",
	  "Description": "NVM BUCK mode shadow register 1",
      "Size": "0x1",
      "Fields": [
        {
          "Bit": {
            "Name": "BUCK1_PREG_MODE",
            "Description": "BUCK1 operates in high power mode (HP)\nlow power mode (LP)\nforced PWM mode (CCM)",
            "BitOffset": "0x0",
            "BitWidth": "0x2",
            "Access": "RW",
            "PossibleValues": {
              "0x0": "BUCK1 HP",
              "0x1": "BUCK1 LP",
			  "0x2": "BUCK1 CCM"
            }
          }
        },
        {
          "Bit": {
            "Name": "BUCK2_PREG_MODE",
            "Description": "BUCK2 operates in high power mode (HP)\nlow power mode (LP)\nforced PWM mode (CCM)",
            "BitOffset": "0x2",
            "BitWidth": "0x2",
            "Access": "RW",
            "PossibleValues": {
              "0x0": "BUCK2 HP",
              "0x1": "BUCK2 LP",
			  "0x2": "BUCK2 CCM"
            }
          }
        }
      ]
    },
	
	{
      "Address": "0x9B",
      "Name": "FREE_SHR3",
	  "Description": "FREE_SHR3",
      "Size": "0x1",
      "Fields": [
        {
          "Bit": {
            "Name": "FREE3",
            "Description": "-",
            "BitOffset": "0x0",
            "BitWidth": "0x8",
            "Access": "RW"
          }
        }
      ]
    },
	
	{
        "Address": "0x9C",
        "Name": "BUCK1_VOUT_SHR",
        "Description": "NVM BUCK1 mode shadow register 2",
        "Size": "0x1",
        "Fields": [
            {
                "Bit": {
                    "Name": "VOUT",
                    "Description": "NVM BUCK1 output voltage shadow register",
                    "BitOffset": "0x0",
                    "BitWidth": "0x7",
                    "Access": "RW"
                }
            },
			{
                "Bit": {
                    "Name": "BUCK1_VRANGE_CFG",
                    "Description": "BUCK1_VRANGE_CFG.\n0: BUCK1_LV with [0.5V;1.5V] and 10mV programming step\n1: BUCK1_HV with [1.5V;4.2V] and 100mV programming step",
                    "BitOffset": "0x7",
                    "BitWidth": "0x1",
                    "Access": "RW"
                }
            }
        ]
    },
	
    {
        "Address": "0x9D",
        "Name": "BUCK2_VOUT_SHR",
        "Description": "NVM BUCK2 mode shadow register 2",
        "Size": "0x1",
        "Fields": [
            {
                "Bit": {
                    "Name": "VOUT",
                    "Description": "NVM BUCK2 output voltage shadow register",
                    "BitOffset": "0x0",
                    "BitWidth": "0x7",
                    "Access": "RW"
                }
            },
			{
                "Bit": {
                    "Name": "BUCK2_IRANGE_CFG",
                    "Description": "BUCK2_IRANGE_CFG\n0: BUCK2_LT Low load transient range selection\n1: BUCK2_HT High load transient range selection",
                    "BitOffset": "0x7",
                    "BitWidth": "0x1",
                    "Access": "RW"
                }
            }
        ]
    },
	
    {
        "Address": "0x9E",
        "Name": "Reserved",
        "Description": "-",
        "Size": "0x1",
        "Fields": [
            {
                "Bit": {
                    "Name": "Reserved",
                    "Description": "-",
                    "BitOffset": "0x0",
                    "BitWidth": "0x8",
                    "Access": "R"
                }
            }
        ]
    },
	
    {
        "Address": "0x9F",
        "Name": "MAIN_CTRL_SHR3",
        "Description": "NVM BUCK4 mode shadow register 2",
        "Size": "0x1",
        "Fields": [
            {
                "Bit": {
                    "Name": "GPO1_POL",
                    "Description": "GPO1 polarity selection:\n0: GPO1 is active high\n1: GPO1 is active low",
                    "BitOffset": "0x0",
                    "BitWidth": "0x1",
                    "Access": "RW"
                }
            },
			{
                "Bit": {
                    "Name": "GPO2_POL",
                    "Description": "GPO2 polarity selection::\n0: GPO2 is active high\n1: GPO2 is active low",
                    "BitOffset": "0x1",
                    "BitWidth": "0x1",
                    "Access": "RW"
                }
            }
        ]
    },
    {
        "Address": "0xA0",
        "Name": "RANK_SHR9",
        "Description": "RANK_SHR9",
        "Size": "0x1",
        "Fields": [
            {
                "Bit": {
                    "Name": "GPO1_RANK",
                    "Description": "GPO1_RANK",
                    "BitOffset": "0x0",
                    "BitWidth": "0x3",
                    "Access": "RW",
					"PossibleValues": {
					  "0x0": "rank0",
					  "0x1": "rank1",
					  "0x2": "rank2",
					  "0x3": "rank3",
					  "0x4": "rank4",
					  "0x5": "rank5",
					  "0x6": "rank0",
					  "0x7": "rank0"
					}
                }
            },
			{
                "Bit": {
                    "Name": "GPO2_RANK",
                    "Description": "GPO2_RANK",
                    "BitOffset": "0x3",
                    "BitWidth": "0x3",
                    "Access": "RW",
					"PossibleValues": {
					  "0x0": "rank0",
					  "0x1": "rank1",
					  "0x2": "rank2",
					  "0x3": "rank3",
					  "0x4": "rank4",
					  "0x5": "rank5",
					  "0x6": "rank0",
					  "0x7": "rank0"
					}
                }
            }
        ]
    },
	
	{
        "Address": "0xA1",
        "Name": "Reserved",
        "Description": "-",
        "Size": "0x1",
        "Fields": [
            {
                "Bit": {
                    "Name": "Reserved",
                    "Description": "-",
                    "BitOffset": "0x0",
                    "BitWidth": "0x8",
                    "Access": "R"
                }
            }
        ]
    },
	
	{
        "Address": "0xA2",
        "Name": "Reserved",
        "Description": "-",
        "Size": "0x1",
        "Fields": [
            {
                "Bit": {
                    "Name": "Reserved",
                    "Description": "-",
                    "BitOffset": "0x0",
                    "BitWidth": "0x8",
                    "Access": "R"
                }
            }
        ]
    },
	
    {
        "Address": "0xA3",
        "Name": "LDO2_SHR",
        "Description": "LDO2 control shadow register",
        "Size": "0x1",
        "Fields": [
            {
                "Bit": {
                    "Name": "VOUT",
                    "Description": "LDO2 default output voltage settings",
                    "BitOffset": "0x1",
                    "BitWidth": "0x5",
                    "Access": "RW"
                },
                "Bit": {
                    "Name": "BYPASS",
                    "Description": "select default bypass mode operation",
                    "BitOffset": "0x6",
                    "BitWidth": "0x1",
                    "Access": "RW",
                    "PossibleValues": {
                        "0x0": "Normal",
                        "0x1": "Bypass"
                    }
                }
            }
        ]
    },

	{
        "Address": "0xA4",
        "Name": "LDO3_SHR",
        "Description": "LDO3 control shadow register",
        "Size": "0x1",
        "Fields": [
            {
                "Bit": {
                    "Name": "VOUT",
                    "Description": "LDO3 default output voltage settings",
                    "BitOffset": "0x1",
                    "BitWidth": "0x5",
                    "Access": "RW"
                },
                "Bit": {
                    "Name": "BYPASS",
                    "Description": "select default bypass mode operation",
                    "BitOffset": "0x6",
                    "BitWidth": "0x1",
                    "Access": "RW",
                    "PossibleValues": {
                        "0x0": "Normal",
                        "0x1": "Bypass"
                    }
                }
            }
        ]
    },

    {
        "Address": "0xA5",
        "Name": "LDO5_SHR",
        "Description": "LDO5 control shadow register",
        "Size": "0x1",
        "Fields": [
            {
                "Bit": {
                    "Name": "VOUT",
                    "Description": "LDO5 default output voltage settings",
                    "BitOffset": "0x1",
                    "BitWidth": "0x5",
                    "Access": "RW"
                },
                "Bit": {
                    "Name": "BYPASS",
                    "Description": "select default bypass mode operation",
                    "BitOffset": "0x6",
                    "BitWidth": "0x1",
                    "Access": "RW",
                    "PossibleValues": {
                        "0x0": "Normal",
                        "0x1": "Bypass"
                    }
                }
            }
        ]
    },
	
	{
        "Address": "0xA6",
        "Name": "Reserved",
        "Description": "-",
        "Size": "0x1",
        "Fields": [
            {
                "Bit": {
                    "Name": "Reserved",
                    "Description": "-",
                    "BitOffset": "0x0",
                    "BitWidth": "0x8",
                    "Access": "R"
                }
            }
        ]
    },
	
	{
        "Address": "0xA7",
        "Name": "Reserved",
        "Description": "-",
        "Size": "0x1",
        "Fields": [
            {
                "Bit": {
                    "Name": "Reserved",
                    "Description": "-",
                    "BitOffset": "0x0",
                    "BitWidth": "0x8",
                    "Access": "R"
                }
            }
        ]
    },
	
	{
      "Address": "0xA8",
      "Name": "FREE_SHR4",
	  "Description": "FREE_SHR4",
      "Size": "0x1",
      "Fields": [
        {
          "Bit": {
            "Name": "FREE_SHR4",
            "Description": "-",
            "BitOffset": "0x0",
            "BitWidth": "0x8",
            "Access": "RW"
          }
        }
      ]
    },
	
	{
      "Address": "0xA9",
      "Name": "PD_SHR1",
	  "Description": "NVM pull-down control shadow register 1",
      "Size": "0x1",
      "Fields": [
        {
          "Bit": {
            "Name": "BUCK1_PD",
            "Description": "BUCK1 pull-down (PD) selection",
            "BitOffset": "0x0",
            "BitWidth": "0x2",
            "Access": "RW",
            "PossibleValues": {
              "0x0": "No PD",
              "0x1": "Slow PD active",
			  "0x2": "Fast PD active",
			  "0x3": "Slow PD forced active"
            }
          }
        },
        {
          "Bit": {
            "Name": "BUCK2_PD",
            "Description": "BUCK2 pull-down (PD) selection",
            "BitOffset": "0x2",
            "BitWidth": "0x2",
            "Access": "RW",
            "PossibleValues": {
              "0x0": "No PD",
              "0x1": "Slow PD active",
			  "0x2": "Fast PD active",
			  "0x3": "Slow PD forced active"
            }
          }
        }
      ]
    },
	
	{
      "Address": "0xAA",
      "Name": "FREE_SHR5",
	  "Description": "FREE_SHR5",
      "Size": "0x1",
      "Fields": [
        {
          "Bit": {
            "Name": "FREE_SHR5",
            "Description": "-",
            "BitOffset": "0x0",
            "BitWidth": "0x8",
            "Access": "RW"
          }
        }
      ]
    },
	
	{
      "Address": "0xAB",
      "Name": "PD_SHR3",
	  "Description": "NVM pull-down control shadow register 3",
      "Size": "0x1",
      "Fields": [
		{
          "Bit": {
            "Name": "LDO2_PD",
            "Description": "pull-down active when LDO2 is disabled (EN = 0)",
            "BitOffset": "0x1",
            "BitWidth": "0x1",
            "Access": "RW",
            "PossibleValues": {
              "0x0": "Inactive",
              "0x1": "Active"
            }
          }
        },
		{
          "Bit": {
            "Name": "LDO3_PD",
            "Description": "pull-down active when LDO3 is disabled (EN = 0)",
            "BitOffset": "0x2",
            "BitWidth": "0x1",
            "Access": "RW",
            "PossibleValues": {
              "0x0": "Inactive",
              "0x1": "Active"
            }
          }
        },
		{
          "Bit": {
            "Name": "LDO4_PD",
            "Description": "pull-down active when LDO4 is disabled (EN = 0)",
            "BitOffset": "0x3",
            "BitWidth": "0x1",
            "Access": "RW",
            "PossibleValues": {
              "0x0": "Inactive",
              "0x1": "Active"
            }
          }
        },
		{
          "Bit": {
            "Name": "LDO5_PD",
            "Description": "pull-down active when LDO5 is disabled (EN = 0)",
            "BitOffset": "0x4",
            "BitWidth": "0x1",
            "Access": "RW",
            "PossibleValues": {
              "0x0": "Inactive",
              "0x1": "Active"
            }
          }
        }
      ]
    },
	
	{
      "Address": "0xAC",
      "Name": "BUCKS_IOUT_SHR1",
	  "Description": "NVM BUCKs output current limitation shadow register 1",
      "Size": "0x1",
      "Fields": [
        {
          "Bit": {
            "Name": "BUCK1_ILIM",
            "Description": "BUCK1 output current limitation",
            "BitOffset": "0x0",
            "BitWidth": "0x2",
            "Access": "RW",
            "PossibleValues": {
              "0x0": "500mA",
              "0x1": "1000mA",
			  "0x2": "1500mA",
              "0x3": "2000mA"
            }
          }
        },
        {
          "Bit": {
            "Name": "BUCK2_ILIM",
            "Description": "BUCK2 output current limitation",
            "BitOffset": "0x2",
            "BitWidth": "0x2",
            "Access": "RW",
            "PossibleValues": {
              "0x0": "500mA",
              "0x1": "1000mA",
			  "0x2": "1500mA",
              "0x3": "2000mA"
            }
          }
        }
      ]
    },
	
	{
      "Address": "0xAD",
      "Name": "BUCKS_IOUT_SHR2",
	  "Description": "NVM BUCKs output current limitation shadow register 2",
      "Size": "0x1",
      "Fields": [
		{
          "Bit": {
            "Name": "HICCUP_DLY",
            "Description": "HICCUP_DLY output current limitation",
            "BitOffset": "0x6",
            "BitWidth": "0x2",
            "Access": "RW",
            "PossibleValues": {
              "0x0": "0ms",
              "0x1": "100ms",
			  "0x2": "500ms",
              "0x3": "1000ms"
            }
          }
        }
      ]
    },
	
	{
      "Address": "0xAE",
      "Name": "LDOS_IOUT_SHR",
	  "Description": "NVM LDOs output current limitation shadow register",
      "Size": "0x1",
      "Fields": [
        {
          "Bit": {
            "Name": "LDO2_ILIM",
            "Description": "LDO2 output current limitation",
            "BitOffset": "0x0",
            "BitWidth": "0x2",
            "Access": "RW",
            "PossibleValues": {
              "0x0": "50mA",
              "0x1": "100mA",
			  "0x2": "200mA",
              "0x3": "400mA"
            }
          }
        },
        {
          "Bit": {
            "Name": "LDO5_ILIM",
            "Description": "LDO5 output current limitation",
            "BitOffset": "0x2",
            "BitWidth": "0x2",
            "Access": "RW",
            "PossibleValues": {
              "0x0": "50mA",
              "0x1": "100mA",
			  "0x2": "200mA",
              "0x3": "400mA"
            }
          }
        }
      ]
    },
	
	{
      "Address": "0xAF",
      "Name": "FS_OCP_SHR1",
	  "Description": "NVM fail-safe overcurrent protection shadow register 1",
      "Size": "0x1",
      "Fields": [
        {
          "Bit": {
            "Name": "FS_OCP_BUCK1",
            "Description": "BUCK1 OCP management mode selection\nOCP Hiccup mode (Level 0)\nOCP fail-safe PMIC turn-off (Level 1)",
            "BitOffset": "0x0",
            "BitWidth": "0x1",
            "Access": "RW",
            "PossibleValues": {
              "0x0": "Level 0",
              "0x1": "Level 1"
            }
          }
        },
		{
          "Bit": {
            "Name": "FS_OCP_BUCK2",
            "Description": "BUCK2 OCP management mode selection\nOCP Hiccup mode (Level 0)\nOCP fail-safe PMIC turn-off (Level 1)",
            "BitOffset": "0x1",
            "BitWidth": "0x1",
            "Access": "RW",
            "PossibleValues": {
              "0x0": "Level 0",
              "0x1": "Level 1"
            }
          }
        }
      ]
    },
	
	{
      "Address": "0xB0",
      "Name": "FS_OCP_SHR2",
	  "Description": "NVM fail-safe overcurrent protection shadow register 2",
      "Size": "0x1",
      "Fields": [
		{
          "Bit": {
            "Name": "FS_OCP_LDO2",
            "Description": "LDO2 OCP management mode selection\nOCP Hiccup mode (Level 0)\nOCP fail-safe PMIC turn-off (Level 1)",
            "BitOffset": "0x1",
            "BitWidth": "0x1",
            "Access": "RW",
            "PossibleValues": {
              "0x0": "Level 0",
              "0x1": "Level 1"
            }
          }
        },
		{
          "Bit": {
            "Name": "FS_OCP_LDO3",
            "Description": "LDO3 OCP management mode selection\nOCP Hiccup mode (Level 0)\nOCP fail-safe PMIC turn-off (Level 1)",
            "BitOffset": "0x2",
            "BitWidth": "0x1",
            "Access": "RW",
            "PossibleValues": {
              "0x0": "Level 0",
              "0x1": "Level 1"
            }
          }
        },
		{
          "Bit": {
            "Name": "FS_OCP_LDO4",
            "Description": "LDO4 OCP management mode selection\nOCP Hiccup mode (Level 0)\nOCP fail-safe PMIC turn-off (Level 1)",
            "BitOffset": "0x3",
            "BitWidth": "0x1",
            "Access": "RW",
            "PossibleValues": {
              "0x0": "Level 0",
              "0x1": "Level 1"
            }
          }
        },
		{
          "Bit": {
            "Name": "FS_OCP_LDO5",
            "Description": "LDO5 OCP management mode selection\nOCP Hiccup mode (Level 0)\nOCP fail-safe PMIC turn-off (Level 1)",
            "BitOffset": "0x4",
            "BitWidth": "0x1",
            "Access": "RW",
            "PossibleValues": {
              "0x0": "Level 0",
              "0x1": "Level 1"
            }
          }
        }
      ]
    },
	
	{
      "Address": "0xB1",
      "Name": "FS_SHR1",
	  "Description": "NVM fail-safe shadow register 1",
      "Size": "0x1",
      "Fields": [
        {
          "Bit": {
            "Name": "PKEY_FLT_CNT_MAX",
            "Description": "Setting of the maximum number of occurrences triggered by a PONKEYn long key press hard-fault source",
            "BitOffset": "0x0",
            "BitWidth": "0x4",
            "Access": "RW"
          }
        },
        {
          "Bit": {
            "Name": "VIN_FLT_CNT_MAX",
            "Description": "Setting of the maximum number of occurrences triggered by a VIN falling below VINOK_Fall hard-fault source",
            "BitOffset": "0x4",
            "BitWidth": "0x4",
            "Access": "RW"
          }
        }
      ]
    },
	
	{
      "Address": "0xB2",
      "Name": "FS_SHR2",
	  "Description": "NVM fail-safe shadow register 2",
      "Size": "0x1",
      "Fields": [
        {
          "Bit": {
            "Name": "OCP_FLT_CNT_MAX",
            "Description": "Setting of the maximum number of occurrences triggered by regulator overcurrent hard-fault source",
            "BitOffset": "0x0",
            "BitWidth": "0x4",
            "Access": "RW"
          }
        },
        {
          "Bit": {
            "Name": "TSHDN_FLT_CNT_MAX",
            "Description": "Setting of the maximum number of occurrences triggered by a thermal shutdown hard-fault source",
            "BitOffset": "0x4",
            "BitWidth": "0x4",
            "Access": "RW"
          }
        }
      ]
    },
	
	{
      "Address": "0xB3",
      "Name": "FS_SHR3",
	  "Description": "NVM fail-safe shadow register 3",
      "Size": "0x1",
      "Fields": [
        {
          "Bit": {
            "Name": "WDG_FLT_CNT_MAX",
            "Description": "Setting of the maximum number of occurrences triggered by a watchdog hard-fault source",
            "BitOffset": "0x0",
            "BitWidth": "0x4",
            "Access": "RW"
          }
        },
        {
          "Bit": {
            "Name": "RST_FLT_CNT_TMR",
            "Description": "Setting of the maximum number of occurrences triggered by a thermal shutdown hard-fault source",
            "BitOffset": "0x4",
            "BitWidth": "0x2",
            "Access": "RW",
			"PossibleValues": {
              "0x0": "Disabled",
              "0x1": "1 minutes",
			  "0x2": "6 minutes",
              "0x3": "60 minutes"
            }
          }
        },
		{
          "Bit": {
            "Name": "FAIL_SAFE_LOCK_DIS",
            "Description": "Disable fail-safe lock state (pass through)",
            "BitOffset": "0x6",
            "BitWidth": "0x1",
            "Access": "RW",
			"PossibleValues": {
              "0x0": "Enabled",
              "0x1": "Disabled"
            }
          }
        }
      ]
    },
	
	{
      "Address": "0xB4",
      "Name": "Reserved",
	  "Description": "-",
      "Size": "0x1",
      "Fields": [
        {
          "Bit": {
            "Name": "Reserved",
            "Description": "-",
            "BitOffset": "0x0",
            "BitWidth": "0x8",
            "Access": "R"
          }
        }
      ]
    },
	
	{
      "Address": "0xB5",
      "Name": "I2C_ADDR_SHR",
	  "Description": "NVM I2C device address shadow register",
      "Size": "0x1",
      "Fields": [
        {
          "Bit": {
            "Name": "I2C_ADDR",
            "Description": "PMIC I2C address\nThe content of this register take effect after the NVM programming command",
            "BitOffset": "0x0",
            "BitWidth": "0x7",
            "Access": "RW"
          }
        },
        {
          "Bit": {
            "Name": "LOCK_NVM",
            "Description": "NVM write access lock\nThe LOCK_NVM bit takes effect on both shadow registers write and NVM programming command",
            "BitOffset": "0x7",
            "BitWidth": "0x1",
            "Access": "RW",
			"PossibleValues": {
              "0x0": "No",
              "0x1": "Yes"
            }
          }
        }
      ]
    },
	
	{
      "Address": "0xB6",
      "Name": "NVM_USER_SHR1",
	  "Description": "User free shadow register 1",
      "Size": "0x1",
      "Fields": [
        {
          "Bit": {
            "Name": "NVM_USER1",
            "Description": "User defined value\nFree usage scratch registers save end-product application data in the NVM",
            "BitOffset": "0x0",
            "BitWidth": "0x8",
            "Access": "RW"
          }
        }
      ]
    },
	
	{
      "Address": "0xB7",
      "Name": "NVM_USER_SHR2",
	  "Description": "User free shadow register 2",
      "Size": "0x1",
      "Fields": [
        {
          "Bit": {
            "Name": "NVM_USER2",
            "Description": "User defined value\nFree usage scratch registers save end-product application data in the NVM",
            "BitOffset": "0x0",
            "BitWidth": "0x8",
            "Access": "RW"
          }
        }
      ]
    }
  ]
}